open_spotify_dl
